sterces/__init__.py
sterces/constants.py
sterces/db.py
sterces/foos.py
sterces/py.typed
sterces-0.1.3.dist-info/LICENSE
sterces-0.1.3.dist-info/METADATA
sterces-0.1.3.dist-info/WHEEL
sterces-0.1.3.dist-info/RECORD
