Metadata-Version: 2.3
Name: sterces
Version: 0.1.3
Summary: Wrapper for pykeepass library
License: MIT
Keywords: secrets,keepass
Author: Quien Sabe
Author-email: qs5579@mail.com
Requires-Python: >=3.10,<4.0
Classifier: Development Status :: 4 - Beta
Classifier: Environment :: Console
Classifier: Intended Audience :: End Users/Desktop
Classifier: Intended Audience :: System Administrators
Classifier: License :: OSI Approved :: MIT License
Classifier: Operating System :: POSIX :: Linux
Classifier: Programming Language :: Python :: 3
Classifier: Programming Language :: Python :: 3.10
Classifier: Programming Language :: Python :: 3.11
Classifier: Programming Language :: Python :: 3.12
Classifier: Programming Language :: Python :: 3.13
Classifier: Programming Language :: Python :: 3 :: Only
Classifier: Topic :: Utilities
Classifier: Typing :: Typed
Requires-Dist: dateparser (>=1.2.1,<2.0.0)
Requires-Dist: loguru (>=0.7.3,<0.8.0)
Requires-Dist: pykeepass (>=4.1.1.post1,<5.0.0)
Requires-Dist: pyotp (>=2.9.0,<3.0.0)
Project-URL: Documentation, https://sterces.readthedocs.io/en/stable
Project-URL: Homepage, https://github.com/wtfo-guru/sterces
